cosimulation/__init__.py
cosimulation-0.0.0.dist-info/LICENSE
cosimulation-0.0.0.dist-info/METADATA
cosimulation-0.0.0.dist-info/WHEEL
cosimulation-0.0.0.dist-info/top_level.txt
cosimulation-0.0.0.dist-info/RECORD
